LICENSE
MANIFEST.in
README.md
setup.cfg
setup.py
tox.ini
src/tfkerassurgeon/__init__.py
src/tfkerassurgeon/identify.py
src/tfkerassurgeon/operations.py
src/tfkerassurgeon/surgeon.py
src/tfkerassurgeon/utils.py
src/tfkerassurgeon.egg-info/PKG-INFO
src/tfkerassurgeon.egg-info/SOURCES.txt
src/tfkerassurgeon.egg-info/dependency_links.txt
src/tfkerassurgeon.egg-info/requires.txt
src/tfkerassurgeon.egg-info/top_level.txt
src/tfkerassurgeon/examples/__init__.py
src/tfkerassurgeon/examples/inception_flowers_prune.py
src/tfkerassurgeon/examples/inception_flowers_tune.py
src/tfkerassurgeon/examples/lenet_mnist.py
tests/test_surgeon.py
tests/test_utils.py