Metadata-Version: 2.1
Name: tfkerassurgeon
Version: 0.2.0
Summary: A library for performing network surgery on trained tf.Keras models. Useful for deep neural network pruning.
Home-page: https://github.com/Raukk/tf-keras-surgeon
Author: Ben Whetton
Author-email: 
License: MIT
Platform: UNKNOWN
Requires-Python: >=3
Provides-Extra: examples
